pyrvs/__init__.py
pyrvs/__init__WORKING.py
pyrvs/pyrvs.cp310-win_amd64.pyd
pyrvs-0.395.dist-info/METADATA
pyrvs-0.395.dist-info/WHEEL
pyrvs-0.395.dist-info/top_level.txt
pyrvs-0.395.dist-info/RECORD
