Metadata-Version: 2.1
Name: pyrvs
Version: 0.395
Summary: Reference View Synthesizer (RVS) python package.
Home-page: https://gitlab.com/mpeg-i-visual/rvs
Author: Daniele Bonatto, Sarah Fachada
Author-email: daniele.bonatto@ulb.be
License: MIT
Classifier: Programming Language :: Python :: 3
Classifier: License :: OSI Approved :: MIT License
Classifier: Operating System :: OS Independent
Requires-Python: >=3.6
Requires-Dist: pybind11>=2.6.0
Requires-Dist: numpy
Requires-Dist: opencv-python
